agentlens/__init__.py
agentlens/cli.py
agentlens/client.py
agentlens/context.py
agentlens/evaluation.py
agentlens/inference.py
agentlens/py.typed
agentlens-0.1.43.dist-info/entry_points.txt
agentlens-0.1.43.dist-info/LICENSE
agentlens-0.1.43.dist-info/METADATA
agentlens-0.1.43.dist-info/WHEEL
agentlens-0.1.43.dist-info/RECORD
