Metadata-Version: 2.1
Name: agentlens
Version: 0.1.43
Summary: lightweight abstractions for building agent scaffolds
Author: danielreuter
Author-email: dreuter14@gmail.com
Requires-Python: >=3.12
Classifier: Programming Language :: Python :: 3
Classifier: Programming Language :: Python :: 3.12
Requires-Dist: mypy (>=1.12.1,<2.0.0)
Requires-Dist: pydantic (>=2.10.4,<3.0.0)
Requires-Dist: pytest-asyncio (>=0.24.0,<0.25.0)
Requires-Dist: python-dotenv (>=1.0.1,<2.0.0)
Requires-Dist: ruff (>=0.7.1,<0.8.0)
Requires-Dist: tenacity (>=9.0.0,<10.0.0)
Requires-Dist: typer (>=0.12.5,<0.13.0)
